<?xml version="1.0" encoding="utf-8"?>
<!--XML DATA CREATED 2017-10-08 10:57:18-->
<ru><NAME><![CDATA[Имя]]></NAME><VALUE><![CDATA[Значение]]></VALUE><CHANGELANGUAGE><![CDATA[Изменить язык]]></CHANGELANGUAGE><BACK><![CDATA[Свернуть]]></BACK><TESTING><![CDATA[Тестирование]]></TESTING><LANGUAGES><![CDATA[Языки]]></LANGUAGES><TESET><![CDATA[Тест]]></TESET><LOGOUT><![CDATA[Выход]]></LOGOUT><BACKEND_TITLE><![CDATA[CmsTile]]></BACKEND_TITLE><SAVE_COMPLETE><![CDATA[Сохранено]]></SAVE_COMPLETE><CLOSE_TAB_CONFIRM><![CDATA[Закрыть?]]></CLOSE_TAB_CONFIRM><SHOW_ITEMS_PERPAGE><![CDATA[Строк на странице]]></SHOW_ITEMS_PERPAGE><FOUND_ROWS><![CDATA[Найдено]]></FOUND_ROWS><TO_ATTACH_FILE><![CDATA[Чтобы прикрепить файл, вам надо сохранить этот пункт]]></TO_ATTACH_FILE><EDIT_OFFER><![CDATA[Редактировать]]></EDIT_OFFER><OFFER_EXP_DATE><![CDATA[Срок действия]]></OFFER_EXP_DATE><OFFER_CURRENCY><![CDATA[Валюта]]></OFFER_CURRENCY><OFFER_PRICE><![CDATA[Цена]]></OFFER_PRICE><OFFER_YEAR_ISUS><![CDATA[Год]]></OFFER_YEAR_ISUS><OFFER_MODEL><![CDATA[Модель]]></OFFER_MODEL><OFFER_BRAND><![CDATA[Марка]]></OFFER_BRAND><OFFER_ID><![CDATA[Id]]></OFFER_ID><SITEUSER><![CDATA[Пользователь]]></SITEUSER><DEALER><![CDATA[Дилер]]></DEALER><FEATURED><![CDATA[Рекомендуемые]]></FEATURED><HIGHLIGHT><![CDATA[Выделите]]></HIGHLIGHT><FILED_SRTAT_DATE><![CDATA[Начало]]></FILED_SRTAT_DATE><FILED_CAR_BRAND_MODEL><![CDATA[Модель]]></FILED_CAR_BRAND_MODEL><FILED_CAR_BRAND><![CDATA[Марка]]></FILED_CAR_BRAND><SELECT_MONTH><![CDATA[Месяц]]></SELECT_MONTH><CLOSE><![CDATA[Закрыть]]></CLOSE><SELECT_YEAR><![CDATA[Выберите]]></SELECT_YEAR><FILL_ALL_INPUTS><![CDATA[Пожалуйста, заполните все поля]]></FILL_ALL_INPUTS><CONFIRM_DELETE><![CDATA[Удалить?]]></CONFIRM_DELETE><__ERROR_1024__MKPASSWORD><![CDATA[Пароль не надежен]]></__ERROR_1024__MKPASSWORD><__ERROR_274__><![CDATA[Не действующий e-mail]]></__ERROR_274__><MORE><![CDATA[Подробнее]]></MORE><FE_ENTER><![CDATA[Войти]]></FE_ENTER><LOG_OUT><![CDATA[Выйти]]></LOG_OUT><FIELD_UNIQUE_ERROR><![CDATA[Ошибка уникальности]]></FIELD_UNIQUE_ERROR><__ERROR_REQUIRED__><![CDATA[Объязательный]]></__ERROR_REQUIRED__><REMOVE_SELECTED_OFFERS><![CDATA[Удалить выделенные]]></REMOVE_SELECTED_OFFERS><FILED_FUEL><![CDATA[Топливо]]></FILED_FUEL><DATE_OF_MANUFACTURE><![CDATA[Дата производства]]></DATE_OF_MANUFACTURE><BY_CONTRACT><![CDATA[Договорная]]></BY_CONTRACT><PID><![CDATA[Исходный элемент]]></PID><PID><![CDATA[ Исходный элемент]]></PID><OFFERSDEALER1><![CDATA[Предложения дилеров]]></OFFERSDEALER1><OFFERSFEATURED><![CDATA[Специальные позиции]]></OFFERSFEATURED><SIMPLEOFFERS><![CDATA[Позиции]]></SIMPLEOFFERS><MODIFICATION><![CDATA[Модификация]]></MODIFICATION><RUDDER><![CDATA[Руль]]></RUDDER><GEARBOX><![CDATA[КПП]]></GEARBOX><IMAGE><![CDATA[Фото]]></IMAGE><FILED_RELEASE_DATE_YEAR><![CDATA[Год]]></FILED_RELEASE_DATE_YEAR><FILED_RELEASE_DATE_MONTH><![CDATA[Месяц]]></FILED_RELEASE_DATE_MONTH><MENSURATION_OF_VOLUME><![CDATA[л.]]></MENSURATION_OF_VOLUME><FILED_CONTRACT><![CDATA[Договорная]]></FILED_CONTRACT><FILED_PRICE><![CDATA[Цена]]></FILED_PRICE><SELECT_FILED_CURRENCY><![CDATA[Валюта]]></SELECT_FILED_CURRENCY><FRON_USER_WELCOME><![CDATA[Добро пожаловать]]></FRON_USER_WELCOME><LOGIN><![CDATA[Логин]]></LOGIN><PROFILE><![CDATA[Моя страница]]></PROFILE><MYCARS><![CDATA[Мои объявления]]></MYCARS><REGISTRATION><![CDATA[Регистрация]]></REGISTRATION><FORGOT><![CDATA[Забыли пароль?]]></FORGOT><USER_LOGIN><![CDATA[Логин]]></USER_LOGIN><USER_PASSWORD><![CDATA[Пароль]]></USER_PASSWORD><TOP_SEARCH><![CDATA[Поиск]]></TOP_SEARCH><USER_SUBMIT><![CDATA[Подтвердить]]></USER_SUBMIT><USER_NAME><![CDATA[Имя]]></USER_NAME><USER_EMAIL><![CDATA[Эл. почта]]></USER_EMAIL><USER_PHONE1><![CDATA[Телефон]]></USER_PHONE1><USER_PHONE2><![CDATA[Телефон]]></USER_PHONE2><USER_RE_PASSWORD><![CDATA[Повторите пароль]]></USER_RE_PASSWORD><USER_CURRENT_CAR><![CDATA[ Марка Вашего автомобиля]]></USER_CURRENT_CAR><USER_CURRENT_CAR><![CDATA[Модель]]></USER_CURRENT_CAR><CHANGEPASSWORD><![CDATA[Изменить пароль]]></CHANGEPASSWORD><OLD_PASSWORD><![CDATA[Текущий пароль]]></OLD_PASSWORD><DATA_PASSWORD><![CDATA[Новый пароль]]></DATA_PASSWORD><LAST_PAGE><![CDATA[Последняя страница]]></LAST_PAGE><FIRST_PAGE><![CDATA[Первая страница]]></FIRST_PAGE><FILED_MODIFICATION><![CDATA[Модификация]]></FILED_MODIFICATION><FILED_ENGINEVOLUMEMENSURATION><![CDATA[Двигатель]]></FILED_ENGINEVOLUMEMENSURATION><NEW><![CDATA[Новый]]></NEW><FILED_STATE><![CDATA[Состояние]]></FILED_STATE><SELECT_CAR_BRAND><![CDATA[Выберите]]></SELECT_CAR_BRAND><FILED_CAR_BRAND_MODEL><![CDATA[Модель]]></FILED_CAR_BRAND_MODEL><SELECT_STATE><![CDATA[Выберите]]></SELECT_STATE><FILED_BODY><![CDATA[Кузов]]></FILED_BODY><SELECT_BODY><![CDATA[Выберите]]></SELECT_BODY><FILED_DRIVE><![CDATA[Привод]]></FILED_DRIVE><SELECT_DRIVE><![CDATA[Выберите]]></SELECT_DRIVE><FILED_RUDDER><![CDATA[Руль]]></FILED_RUDDER><SELECT_RUDDER><![CDATA[Выберите]]></SELECT_RUDDER><FILED_GEARBOX><![CDATA[Коробка передач]]></FILED_GEARBOX><SELECT_GEARBOX><![CDATA[Выберите]]></SELECT_GEARBOX><FILED_WARRANTY><![CDATA[Гарантия]]></FILED_WARRANTY><SELECT_WARRANTY><![CDATA[Выберите]]></SELECT_WARRANTY><SELECT_CAR_MODEL><![CDATA[Выберите]]></SELECT_CAR_MODEL><FILED_ENGINE><![CDATA[Двигатель]]></FILED_ENGINE><FILED_CUSTOMS><![CDATA[Таможенный статус]]></FILED_CUSTOMS><SELECT_CUSTOMS><![CDATA[Выберите]]></SELECT_CUSTOMS><FILED_MILAGE><![CDATA[Пробег]]></FILED_MILAGE><FILED_BARGAINING><![CDATA[Торг]]></FILED_BARGAINING><SELECT_BARGAINING><![CDATA[Выберите]]></SELECT_BARGAINING><FILED_COLOR><![CDATA[Цвет]]></FILED_COLOR><SELECT_COLOR><![CDATA[Выберите]]></SELECT_COLOR><FILED_OPTIONS><![CDATA[Опции]]></FILED_OPTIONS><DESCRIPTION><![CDATA[Описание]]></DESCRIPTION><FILED_PHOTOS><![CDATA[Остальные фото]]></FILED_PHOTOS><FILED_DURATION><![CDATA[Срок действия]]></FILED_DURATION><SELECT_DURATION><![CDATA[Выберите]]></SELECT_DURATION><FROM><![CDATA[От]]></FROM><UNTIL><![CDATA[До]]></UNTIL><NEW_NOT_USED><![CDATA[Новый]]></NEW_NOT_USED><SALER><![CDATA[Продавец]]></SALER><HIGHLIGHTS><![CDATA[Основные характеристики]]></HIGHLIGHTS><COMPLETION><![CDATA[Комплектация]]></COMPLETION><START_DATE_DESC><![CDATA[убыванию даты  регистрации]]></START_DATE_DESC><START_DATE_ASC><![CDATA[возрастанию даты регистрации]]></START_DATE_ASC><PRICE_DESC><![CDATA[убыванию цены]]></PRICE_DESC><PRICE_ASC><![CDATA[возрастанию цены]]></PRICE_ASC><YEAR_DESC><![CDATA[убыванию года производства]]></YEAR_DESC><YEAR_ASC><![CDATA[возрастанию года производства]]></YEAR_ASC><MESSAGE><![CDATA[Сообщение]]></MESSAGE><SUBJECT><![CDATA[Тема]]></SUBJECT><BACK_TO_CATEGORY><![CDATA[Назад]]></BACK_TO_CATEGORY><EMAIL_ADDRESS_INVALID><![CDATA[Пожалуйста, введите существующий адрес]]></EMAIL_ADDRESS_INVALID><ONLY_DIGITS><![CDATA[Пожалуйста, введите только цифры]]></ONLY_DIGITS><USER_CURRENT_CAR><![CDATA[Марка Вашего автомобиля]]></USER_CURRENT_CAR><USER_CURRENT_CAR><![CDATA[Марка Вашего  автомобиля]]></USER_CURRENT_CAR><YOUR_PASSWORD_MUST_BE><![CDATA[Пожалуйста, введите пароль не менее 5 символов]]></YOUR_PASSWORD_MUST_BE><PLEASE_ENTER_THE_SAME_PASSWORD_AS_ABOVE><![CDATA[Пожалуйста, введите верный пароль]]></PLEASE_ENTER_THE_SAME_PASSWORD_AS_ABOVE><LOGIN_PASSWORD_ERROR><![CDATA[Неверный логин или пароль]]></LOGIN_PASSWORD_ERROR><FILED_BARGAINING_NUMBER><![CDATA[Введите цифры]]></FILED_BARGAINING_NUMBER><FILED_CAR_BRAND_REQUIRED><![CDATA[Выберите марку]]></FILED_CAR_BRAND_REQUIRED><FILED_MODIFICATION_REQUIRED><![CDATA[Изменение обязательные поля]]></FILED_MODIFICATION_REQUIRED><FILED_BARGAINING_FILED_BODY><![CDATA[Пожалуйста, выберите кузов]]></FILED_BARGAINING_FILED_BODY><FILED_DRIVE_BODY_REQUIRED><![CDATA[Пожалуйста, выберите кузов]]></FILED_DRIVE_BODY_REQUIRED><FILED_RUDDER_REQUIRED><![CDATA[Руль обязательные поля]]></FILED_RUDDER_REQUIRED><FILED_WARRANTY_REQUIRED><![CDATA[Гарантия обязательные поля]]></FILED_WARRANTY_REQUIRED><FILED_RELEASE_DATE_YEAR_REQUIRED><![CDATA[Введите год]]></FILED_RELEASE_DATE_YEAR_REQUIRED><FILED_RELEASE_DATE_MONTH_REQUIRED><![CDATA[Месяц обязательные поля]]></FILED_RELEASE_DATE_MONTH_REQUIRED><FILED_BARGAINING_REQUIRED><![CDATA[Торг обязательное поле]]></FILED_BARGAINING_REQUIRED><FILED_MILAGE_REQUIRED><![CDATA[Введите пробег]]></FILED_MILAGE_REQUIRED><FILED_CURRENCY><![CDATA[Выберите валюту]]></FILED_CURRENCY><FILED_DURATION_REQUIRED><![CDATA[Пожалуйста, выберите срок действия]]></FILED_DURATION_REQUIRED><ERR_NAME><![CDATA[Пожалуйста, введите имя]]></ERR_NAME><ADVANCED_SEARCH><![CDATA[Расширенный поиск]]></ADVANCED_SEARCH><ERR_EMAIL><![CDATA[Пожалуйста, введите e-mail]]></ERR_EMAIL><ERR_SUBJECT><![CDATA[Пожалуйста, введите тему]]></ERR_SUBJECT><ERR_MESSAGE><![CDATA[Пожалуйста, введите сообщение]]></ERR_MESSAGE><ERR_CAPTCHA><![CDATA[Пожалуйста, введите верный код]]></ERR_CAPTCHA><USER_CURRENT_CAR_MODEL><![CDATA[Модель]]></USER_CURRENT_CAR_MODEL><SUBSCRIBE_NEWSLETTER><![CDATA[Подписаться на рассылки]]></SUBSCRIBE_NEWSLETTER><USER_DATE_OF_BIRTH><![CDATA[Дата рождения]]></USER_DATE_OF_BIRTH><SELECT_DAY><![CDATA[День]]></SELECT_DAY><MAX_VIEW_QTY><![CDATA[Макс. кол. показов]]></MAX_VIEW_QTY><SELECT_YEAR><![CDATA[Год]]></SELECT_YEAR><USER_DREAM_BRAND><![CDATA[Марка Вашего будущего автомобиля]]></USER_DREAM_BRAND><SELECT_DREAM_BRAND><![CDATA[Выберите]]></SELECT_DREAM_BRAND><USER_DREAM_MODEL><![CDATA[Модель]]></USER_DREAM_MODEL><SELECT_DREAM_MODEL><![CDATA[Выберите]]></SELECT_DREAM_MODEL><CAR_TYPE><![CDATA[Тип]]></CAR_TYPE><ALL_NEW_USED><![CDATA[Все новые и подержанные]]></ALL_NEW_USED><CAR_MAKE><![CDATA[Марка]]></CAR_MAKE><ALL_MAKES><![CDATA[Не важно]]></ALL_MAKES><CAR_MODEL><![CDATA[Модель]]></CAR_MODEL><SELECT_MODEL><![CDATA[Не важно]]></SELECT_MODEL><TO><![CDATA[До]]></TO><CAR_LOCATION><![CDATA[Место]]></CAR_LOCATION><ALL_LOCATIONS><![CDATA[Все страны]]></ALL_LOCATIONS><SEARCH><![CDATA[Найти]]></SEARCH><OFFICIALWEBPAGE><![CDATA[Официальный сайт]]></OFFICIALWEBPAGE><REGIONALWEBPAGE><![CDATA[Армянский сайт]]></REGIONALWEBPAGE><MENSURATION_OF_POWER><![CDATA[л.с.]]></MENSURATION_OF_POWER><FILED_ENGINE_POWER><![CDATA[Мощность]]></FILED_ENGINE_POWER><VALUE_BETWEEN><![CDATA[Значения между]]></VALUE_BETWEEN><AND><![CDATA[И]]></AND><FILED_ENGINE_REQUIRED><![CDATA[Пожалуйста, введите объем двигателя]]></FILED_ENGINE_REQUIRED><FILED_ENGINE_POWER_REQUIRED><![CDATA[Пожалуйста, введите мощность]]></FILED_ENGINE_POWER_REQUIRED><__ERROR_259__><![CDATA[Десятичное число]]></__ERROR_259__><__ERROR_257__><![CDATA[Должно быть целое]]></__ERROR_257__><VIEWCALC><![CDATA[Открыть калькулятор]]></VIEWCALC><FIRSTPAYMENT><![CDATA[Первый взнос]]></FIRSTPAYMENT><PERMONTH><![CDATA[Месячная плата]]></PERMONTH><MONTHCOUNT><![CDATA[Срок погашения кредита, в месяцах]]></MONTHCOUNT><OFFERS><![CDATA[Объявления]]></OFFERS><ORDERBY><![CDATA[Сортировать по]]></ORDERBY><FOUND><![CDATA[Найдено]]></FOUND><INNEWS><![CDATA[В новостях]]></INNEWS><INMENUS><![CDATA[В меню]]></INMENUS><INBARNDSANDMODEL><![CDATA[В каталоге]]></INBARNDSANDMODEL><MONTHS><![CDATA[Месяцы]]></MONTHS><SELECT_OTHER_MODEL><![CDATA[Выберите]]></SELECT_OTHER_MODEL><CHANGE_SEARCH_PARAMS><![CDATA[Изменить критерии поиска]]></CHANGE_SEARCH_PARAMS><CLICK_FOR_REMOVE_PARAM><![CDATA[Нажмите, чтобы удалить следующие критерии поиска]]></CLICK_FOR_REMOVE_PARAM><VIEWS_QTY><![CDATA[Кол. показов]]></VIEWS_QTY><REMAINING_DAYS><![CDATA[День (дней)]]></REMAINING_DAYS><TODAY><![CDATA[Сегодня]]></TODAY><SEARCH_LANGDATA><![CDATA[Search Language Data ]]></SEARCH_LANGDATA><CAR_SEARCH><![CDATA[Поиск автомобилей]]></CAR_SEARCH><SELECT_ANY><![CDATA[Не важно]]></SELECT_ANY><NONESELECTED><![CDATA[Выберите]]></NONESELECTED><SELECTALLTEXT><![CDATA[Не важно]]></SELECTALLTEXT><MENSURATION_OF_POWER_KW><![CDATA[кВт]]></MENSURATION_OF_POWER_KW><MODELS><![CDATA[Модели]]></MODELS><URGENT_SALE><![CDATA[СРОЧНО ПРОДАЮТСЯ]]></URGENT_SALE><ALL_BRANDS><![CDATA[Все марки]]></ALL_BRANDS><USER_RESET><![CDATA[Сброс]]></USER_RESET><CURENCY_RATES><![CDATA[Курс валюты]]></CURENCY_RATES><CAR_BRANDS><![CDATA[Каталог]]></CAR_BRANDS><FILED_FUEL><![CDATA[Топливо]]></FILED_FUEL><USERNAME><![CDATA[Логин]]></USERNAME><ADD_OFFER><![CDATA[Добавить объявление]]></ADD_OFFER><CAR><![CDATA[Автомобиль]]></CAR><MAIL><![CDATA[Введите e-mail]]></MAIL><BROWSE_><![CDATA[Выберите файл]]></BROWSE_><LAST_NEWS><![CDATA[Последние новости]]></LAST_NEWS><SELECT_YEAR_HOME><![CDATA[Год]]></SELECT_YEAR_HOME><OTHER_MODEL><![CDATA[Другие]]></OTHER_MODEL><YEAR><![CDATA[Год]]></YEAR><MILAGE><![CDATA[Пробег]]></MILAGE><PRICE><![CDATA[Цена]]></PRICE><FILED_STARTDATE><![CDATA[Дата публикации]]></FILED_STARTDATE><PLEASE_PROVIDE_A_PASSWORD><![CDATA[Пожалуйста, введите пароль]]></PLEASE_PROVIDE_A_PASSWORD><PLEASE_ENTER_A_USERNAME><![CDATA[Пожалуйста, введите имя]]></PLEASE_ENTER_A_USERNAME><YOUR_USERNAME_MUST_CONTANIN><![CDATA[Пожалуйста, введите логин не менее 3 символов]]></YOUR_USERNAME_MUST_CONTANIN><EMAIL_ADDRESS_REQUIRED><![CDATA[Пожалуйста, введите е-mail]]></EMAIL_ADDRESS_REQUIRED><DAY_REQUIRED><![CDATA[Пожалуйста, введите день рождения]]></DAY_REQUIRED><MONTH_REQUIRED><![CDATA[Пожалуйста, выберите месяц]]></MONTH_REQUIRED><YEAR_REQUIRED><![CDATA[Пожалуйста, выберите год]]></YEAR_REQUIRED><PHONE_CODE_REQUIRED><![CDATA[Пожалуйста, введите код оператора]]></PHONE_CODE_REQUIRED><PHONE_REQUIRED><![CDATA[Пожалуйста, введите номер телефона]]></PHONE_REQUIRED><CAPTCHA_REQUIRED><![CDATA[Пожалуйста, введите код]]></CAPTCHA_REQUIRED><CAPTCHA_INVLAID><![CDATA[Пожалуйста, введите верный код]]></CAPTCHA_INVLAID><MONTH_1><![CDATA[Январь]]></MONTH_1><MONTH_2><![CDATA[Февраль]]></MONTH_2><MONTH_3><![CDATA[Март]]></MONTH_3><MONTH_4><![CDATA[Апрель]]></MONTH_4><MONTH_5><![CDATA[Май]]></MONTH_5><MONTH_6><![CDATA[Июнь]]></MONTH_6><MONTH_7><![CDATA[Июль]]></MONTH_7><MONTH_8><![CDATA[Август]]></MONTH_8><MONTH_9><![CDATA[Сентябрь]]></MONTH_9><MONTH_10><![CDATA[Октябрь]]></MONTH_10><MONTH_11><![CDATA[Ноябрь]]></MONTH_11><MONTH_12><![CDATA[Декабрь]]></MONTH_12><THIS_USERNAME_EXIST><![CDATA[Данного логина существует]]></THIS_USERNAME_EXIST><EMAIL_ADDRESS_EXIST><![CDATA[Данного адреса уже существует]]></EMAIL_ADDRESS_EXIST><PHONE_CODE_ONLY_DIGITS><![CDATA[Пожалуйста, введите только цифры]]></PHONE_CODE_ONLY_DIGITS><PHONE_ONLY_DIGITS><![CDATA[Пожалуйста, введите только цифры]]></PHONE_ONLY_DIGITS><FILED_GEARBOX_REQUIRED><![CDATA[Выберите тип КП]]></FILED_GEARBOX_REQUIRED><AD_MENSURATION_OF_POWER><![CDATA[кВт]]></AD_MENSURATION_OF_POWER><FILED_POWER><![CDATA[Мощность]]></FILED_POWER><PLEASE_ENTER_A_LOGIN><![CDATA[Пожалуйста, введите логин]]></PLEASE_ENTER_A_LOGIN><CURRENTCAR_BRAND_MODEL_IS_REQUIRED><![CDATA[Пожалуйста, выберите модель]]></CURRENTCAR_BRAND_MODEL_IS_REQUIRED><ERR_EMAIL_EXISTS><![CDATA[Пожалуйста, введите существующий адрес]]></ERR_EMAIL_EXISTS><FILED_MAIN_PHOTOS><![CDATA[Главное фото]]></FILED_MAIN_PHOTOS><COLOR_METALIC><![CDATA[Металлик]]></COLOR_METALIC><FILED_METALIC><![CDATA[Металлик]]></FILED_METALIC><EMAIL_ADDRESS_NOT_EXIST><![CDATA[Данного адреса не существует]]></EMAIL_ADDRESS_NOT_EXIST><INOFFERS><![CDATA[В объявлениях]]></INOFFERS><ALL_CAT_NEWS><![CDATA[Все новости раздела]]></ALL_CAT_NEWS><CAR_CODE><![CDATA[Код]]></CAR_CODE><CAR_CODE><![CDATA[Код]]></CAR_CODE><VIOLATION_CAMERA><![CDATA[Камеры нарушения]]></VIOLATION_CAMERA><BRANDMODEL><![CDATA[Марка Модель]]></BRANDMODEL><DRIVE><![CDATA[Привод]]></DRIVE><BODY><![CDATA[Кузов]]></BODY><WARRANTY><![CDATA[Гарантия]]></WARRANTY><CUSTOMS><![CDATA[Растаможка]]></CUSTOMS><OPTIONS><![CDATA[Опции]]></OPTIONS><TOPMENU><![CDATA[Меню]]></TOPMENU><BOTTOMMENU><![CDATA[Нижнее меню]]></BOTTOMMENU><ALIAS><![CDATA[Имя в URL]]></ALIAS><PRIVATE><![CDATA[Закрытый]]></PRIVATE><LABEL><![CDATA[Название]]></LABEL><LABEL><![CDATA[Название]]></LABEL><CONTENT><![CDATA[Содержание]]></CONTENT><TITLE><![CDATA[Титул]]></TITLE><KEYWORD><![CDATA[Ключевые слова]]></KEYWORD><SAVE><![CDATA[Сохранить]]></SAVE><RESET><![CDATA[Сбросить]]></RESET><SHOW><![CDATA[Показать редактор]]></SHOW><ON><![CDATA[Включен ]]></ON><OFF><![CDATA[Выключен ]]></OFF><USERLOGINACTION><![CDATA[Вход]]></USERLOGINACTION><LEFT><![CDATA[Левый ]]></LEFT><PASSWORD><![CDATA[Пароль]]></PASSWORD><NOTY_MUST_SAVE><![CDATA[необходимо сохранить для внесения изменений]]></NOTY_MUST_SAVE><NOY_ERROR_DURING_SAVE><![CDATA[Возникли ошибки во время сохранения]]></NOY_ERROR_DURING_SAVE><NOY_SAVE_SUCCESS><![CDATA[Операция была успешно завершена]]></NOY_SAVE_SUCCESS><SHORT><![CDATA[Краткое описание]]></SHORT><FULL><![CDATA[Полное описание]]></FULL><GALERY><![CDATA[ГАЛЕРЕЯ]]></GALERY><OFFER_INTERCHANGE><![CDATA[Обмен]]></OFFER_INTERCHANGE><LINK1><![CDATA[Ссылка 1]]></LINK1><LINK2><![CDATA[Ссылка 2]]></LINK2><LINK2><![CDATA[Ссылка 2]]></LINK2><HOME><![CDATA[Главная]]></HOME><ONLINE_CALCULATOR><![CDATA[Онлайн калкулятор]]></ONLINE_CALCULATOR><SERVICESCATEGORY><![CDATA[Услуги-Категория]]></SERVICESCATEGORY><ADDRES><![CDATA[Адрес]]></ADDRES><SRTAT_DATE><![CDATA[Дата начала]]></SRTAT_DATE><END_DATE><![CDATA[Дата окончания]]></END_DATE><GROUP><![CDATA[Группа]]></GROUP><MENU><![CDATA[Меню]]></MENU><COUNT_ADS_IN_GROUP><![CDATA[Количество реклам в группе]]></COUNT_ADS_IN_GROUP><OFFER_PHOTO><![CDATA[Фото]]></OFFER_PHOTO><OFFER_YEAR><![CDATA[Год]]></OFFER_YEAR><OFFER_ENGINE><![CDATA[Двигатель]]></OFFER_ENGINE><OFFER_MILAGE><![CDATA[Пробег]]></OFFER_MILAGE><OFFER_ADD_TO_FAV><![CDATA[Отметит]]></OFFER_ADD_TO_FAV><OFFER_STATE><![CDATA[Состояние]]></OFFER_STATE><OFFER_BODY><![CDATA[Кузов]]></OFFER_BODY><OFFER_COLOR><![CDATA[Цвет]]></OFFER_COLOR><OFFER_DRIVE><![CDATA[Привод]]></OFFER_DRIVE><OFFER_GEARBOX><![CDATA[КПП]]></OFFER_GEARBOX><OFFER_RUDDERS><![CDATA[Руль]]></OFFER_RUDDERS><OFFER_FUEL><![CDATA[Топливо]]></OFFER_FUEL><OFFER_CITY><![CDATA[Город]]></OFFER_CITY><OFFER_WARANTY><![CDATA[Гарантия до]]></OFFER_WARANTY><OFFER_EQUIPMENT_SET><![CDATA[Комплектация автомобиля]]></OFFER_EQUIPMENT_SET><OFFER_CONTACT_INFO><![CDATA[ Контактные данные]]></OFFER_CONTACT_INFO><OFFER_PHONE><![CDATA[Телефон]]></OFFER_PHONE><OFFER_DESCRIPTION><![CDATA[Комментарий владельца]]></OFFER_DESCRIPTION><OFFER_PUBLISHED><![CDATA[Размещено]]></OFFER_PUBLISHED><OFFER_ACTIONS><![CDATA[Пок./ред./Удал.]]></OFFER_ACTIONS><OFFER_MILAGE_KM><![CDATA[км]]></OFFER_MILAGE_KM><QUESTION><![CDATA[Ворпос]]></QUESTION><ANSWER_A><![CDATA[Ответ 1]]></ANSWER_A><ANSWER_B><![CDATA[Ответ 2]]></ANSWER_B><ANSWER_C><![CDATA[Ответ 3]]></ANSWER_C><ANSWER_D><![CDATA[Ответ 4]]></ANSWER_D><ANSWER_E><![CDATA[Ответ 5]]></ANSWER_E><CORRECT_ANSWER><![CDATA[Правильный ответ]]></CORRECT_ANSWER><HINT_FOR_CORRECT_ANSWER><![CDATA[Комментария]]></HINT_FOR_CORRECT_ANSWER><IMAGE_ORIGINAL><![CDATA[Фото ГАИ]]></IMAGE_ORIGINAL><IMAGE_ANSWER_A><![CDATA[Фото-ответ А]]></IMAGE_ANSWER_A><IMAGE_ANSWER_B><![CDATA[Фото-ответ B]]></IMAGE_ANSWER_B><IMAGE_ANSWER_C><![CDATA[Фото-ответ C]]></IMAGE_ANSWER_C><IMAGE_ANSWER_D><![CDATA[Фото-ответ D]]></IMAGE_ANSWER_D><IMAGE_ANSWER_E><![CDATA[Фото-ответ E]]></IMAGE_ANSWER_E><TICKETS><![CDATA[Билеты]]></TICKETS><ADV_SEARCH><![CDATA[Մանրամասն որոնում]]></ADV_SEARCH><LATITUDE><![CDATA[широта]]></LATITUDE><LONGITUDE><![CDATA[ДОЛГОТА]]></LONGITUDE><ANGLE><![CDATA[Угол обзора]]></ANGLE><SPEED_CAMERA><![CDATA[Камера (спидометр)]]></SPEED_CAMERA><WELCOME_MESSAGE><![CDATA[Добро пожаловать %s]]></WELCOME_MESSAGE><PDD_EXAM><![CDATA[Экзамен ПДД]]></PDD_EXAM><ESTIMATED_TIME><![CDATA[Осталось времени:]]></ESTIMATED_TIME><EXAM_QUESTIONS><![CDATA[Вопрос:]]></EXAM_QUESTIONS><QUESTION_NUMBER><![CDATA[Вопрос № %s]]></QUESTION_NUMBER><NEXT_QUESTION><![CDATA[Следующий вопрос]]></NEXT_QUESTION><STAR_EXAM><![CDATA[Начать экзамен]]></STAR_EXAM><STOP_EXAM><![CDATA[Завершить экзамен]]></STOP_EXAM><PDD_MARATHON><![CDATA[Օбучение]]></PDD_MARATHON><MAIN_DATA><![CDATA[Оснавные парамерты]]></MAIN_DATA><OPTIONS_DATA><![CDATA[Комплектация]]></OPTIONS_DATA><IMAGES_DATA><![CDATA[Фотографии]]></IMAGES_DATA><CONTACT_DATA><![CDATA[Контактная информация]]></CONTACT_DATA><OFFER_CUSTOMS_FREE><![CDATA[Растаможка]]></OFFER_CUSTOMS_FREE><IS_USSSR><![CDATA[Российский автомобили]]></IS_USSSR><USSSR_VENDORS><![CDATA[Российские автомобили]]></USSSR_VENDORS><NOT_USSSR_VENDORS><![CDATA[Иномарки]]></NOT_USSSR_VENDORS><SALE_OF_BRAND><![CDATA[Продажа автомобилей]]></SALE_OF_BRAND><RELOAD_CAPTCH><![CDATA[Обновить, если не виден код]]></RELOAD_CAPTCH><MODELS_OF_BRAND><![CDATA[Модельный ряд %s]]></MODELS_OF_BRAND><MAIN_MENU><![CDATA[Главное меню]]></MAIN_MENU><TOPE_MENU><![CDATA[Верхное меню]]></TOPE_MENU><YOU_ARE_LOOKING_FOR><![CDATA[Вы ищите]]></YOU_ARE_LOOKING_FOR><SPECIAL_PROJECTS><![CDATA[Специальные проекты]]></SPECIAL_PROJECTS><YOU_ARE_ANSWERED><![CDATA[Количество ответов – %s.]]></YOU_ARE_ANSWERED><YOU_DURATION><![CDATA[за  %s:%s времени]]></YOU_DURATION><PDD_TICKETS><![CDATA[Экзаменационные билеты]]></PDD_TICKETS><FINSH_TEST><![CDATA[Завершить]]></FINSH_TEST><SAVE_RESULT><![CDATA[Сохранить результат]]></SAVE_RESULT><TRENING><![CDATA[Обучения]]></TRENING><MARATHONE_RESULTS><![CDATA[Результаты с %s по %s ]]></MARATHONE_RESULTS><NO_DATA_FOUND><![CDATA[По запросу ничего не найдено. ]]></NO_DATA_FOUND><CONTINUE_MARATHONE><![CDATA[Продолжить обучения]]></CONTINUE_MARATHONE><LASTET_ADDED><![CDATA[Последние предложения]]></LASTET_ADDED><YOU_WRONG_ARE_ANSWERED><![CDATA[Вы  не ответили на %s вопроса.]]></YOU_WRONG_ARE_ANSWERED><BACK_TO_TOP><![CDATA[На Верх]]></BACK_TO_TOP><ADD_SERVICE><![CDATA[Добавить]]></ADD_SERVICE><POOL><![CDATA[Опрос]]></POOL><ASWER_COMMENT><![CDATA[Комментарий]]></ASWER_COMMENT><USER_NEXT><![CDATA[Далее]]></USER_NEXT><SM3><![CDATA[литр]]></SM3><USE_ORIGINAL_IMAGES><![CDATA[ДП]]></USE_ORIGINAL_IMAGES><USE_OUR_IMAGES><![CDATA[Трансинфо]]></USE_OUR_IMAGES><EXAM_DURATION><![CDATA[Время  прохождения экзамена: %s минут]]></EXAM_DURATION><SELECT_BRAND><![CDATA[Выбрать марку]]></SELECT_BRAND><RESUL_FILTER><![CDATA[Фильтровать результат:]]></RESUL_FILTER><SEARCHDIR_FROM><![CDATA[От]]></SEARCHDIR_FROM><SEARCHDIR_TO><![CDATA[До]]></SEARCHDIR_TO><CITY><![CDATA[Город]]></CITY><STREET><![CDATA[Улица]]></STREET><CAMERA_TYPE><![CDATA[Тип Камеры]]></CAMERA_TYPE><DUBLESIDE><![CDATA[Двусторонний]]></DUBLESIDE><NO_QUESTIONS_FOUND><![CDATA[Извените раздел находится в стадии разработки]]></NO_QUESTIONS_FOUND><ONE_SIDE><![CDATA[Односторонний]]></ONE_SIDE><ONE_SIDE><![CDATA[Односторонний]]></ONE_SIDE><EXAM_ERROR_QTY><![CDATA[Кол-во ошибок: %s]]></EXAM_ERROR_QTY><EXAM_ANSWERS_QTY><![CDATA[Кол-во ответов: %s]]></EXAM_ANSWERS_QTY><EXAM_RETAKE><![CDATA[Пересдать экзамен]]></EXAM_RETAKE><BUY_TICKETS><![CDATA[Выбрать билет]]></BUY_TICKETS><CHOOSE_A_THEME><![CDATA[Выбрать тему]]></CHOOSE_A_THEME><YOU_DONT_PASS_EXAM><![CDATA[Поздравляем! Вы сдали экзамен.]]></YOU_DONT_PASS_EXAM><YOUR_ANSWER><![CDATA[Ваш ответ]]></YOUR_ANSWER><RIGHT_ANSWER><![CDATA[Правильный ответ]]></RIGHT_ANSWER><RIGHT_ANSWER_COMMENT><![CDATA[Коментарый]]></RIGHT_ANSWER_COMMENT><TRUE><![CDATA[Правильно]]></TRUE><WRONG><![CDATA[Ощшибка]]></WRONG><SEARCH_IN_CATALOG><![CDATA[Поиск по каталогу:]]></SEARCH_IN_CATALOG><SEARCH_IN_CATALOG_EXAMPLE><![CDATA[Например, автосалоны]]></SEARCH_IN_CATALOG_EXAMPLE><SEARCH_IN_CAT><![CDATA[Искать]]></SEARCH_IN_CAT><ADD_SERICES><![CDATA[Добавить в каталог]]></ADD_SERICES><CONGRATULATIONS_YOU_PASS_EXAM><![CDATA[К сожалению, Вы не сдали экзамен.]]></CONGRATULATIONS_YOU_PASS_EXAM><TOP_SEARCH_SUBMIT><![CDATA[Искать ]]></TOP_SEARCH_SUBMIT><TOP_SEARCH_RESET><![CDATA[Очистить]]></TOP_SEARCH_RESET><SELECT_CITY><![CDATA[Выберите район]]></SELECT_CITY><SELECT_STREET><![CDATA[Выберите улицу ]]></SELECT_STREET><TURN_OFF_HINTS><![CDATA[Отключить подсказки]]></TURN_OFF_HINTS><WRONG_ANSWERS_PR><![CDATA[Неправильные ответы  ]]></WRONG_ANSWERS_PR><TRUE_ANSWER_PR><![CDATA[Правильные ответы ]]></TRUE_ANSWER_PR><TRUE_ANSWERS_PR><![CDATA[Правильные ответы ]]></TRUE_ANSWERS_PR><LOCATION_AND_ACCESS><![CDATA[Адрес и схема проезда]]></LOCATION_AND_ACCESS><COMPANY_ADDRESS><![CDATA[Адрес:]]></COMPANY_ADDRESS><COMPANY_PHONE><![CDATA[Тел.:]]></COMPANY_PHONE><COMPANY_URL><![CDATA[Сайт:]]></COMPANY_URL><COMPANY_E_MAIL><![CDATA[E-mail:]]></COMPANY_E_MAIL><SALE_OFF_BRANDS><![CDATA[Продажа:]]></SALE_OFF_BRANDS><CUSTOMER_CAR_BRANDS><![CDATA[Марки автомобилей]]></CUSTOMER_CAR_BRANDS><LOAING_LIST><![CDATA[Загрузка ....]]></LOAING_LIST><MANDATORY_NOTICE><![CDATA[Поля, помеченные *, обязательны для заполнения.]]></MANDATORY_NOTICE><CONTACT_DETAILS><![CDATA[Контактные данные лица, производящего регистрацию:]]></CONTACT_DETAILS><CONTACT_DETAILS_NAME><![CDATA[Имя:]]></CONTACT_DETAILS_NAME><CONTACT_DETAILS_PHONE><![CDATA[Телефон:]]></CONTACT_DETAILS_PHONE><CONTACT_DETAILS_EMAIL><![CDATA[E-mail:]]></CONTACT_DETAILS_EMAIL><INFORMATION_ABOUT_THE_COMPANY><![CDATA[Информация о компании:]]></INFORMATION_ABOUT_THE_COMPANY><COMPANY_NAME><![CDATA[Название компании:]]></COMPANY_NAME><IDRUBRIC_LABEL><![CDATA[Рубрика:]]></IDRUBRIC_LABEL><E_MAIL_LABEL><![CDATA[E-mail:]]></E_MAIL_LABEL><PHONE_LABEL><![CDATA[Телефон:]]></PHONE_LABEL><WEB_PAGE_LABEL><![CDATA[Сайт (начиная с http://):]]></WEB_PAGE_LABEL><ADDRESS_LABEL><![CDATA[Адрес:]]></ADDRESS_LABEL><SHORT_DESC_LABEL_LABEL><![CDATA[Краткое описание:]]></SHORT_DESC_LABEL_LABEL><ENTER_THE_CODE_SHOWN_BELOW><![CDATA[Введите код, указанный ниже:]]></ENTER_THE_CODE_SHOWN_BELOW><CARS><![CDATA[Автопродажа]]></CARS><CARS><![CDATA[Автопродажа]]></CARS><CARS><![CDATA[Автопродажа]]></CARS><WELCOME><![CDATA[Добро Пожаловать]]></WELCOME><ACCOUNT_LOGIN><![CDATA[Вы можете войти, используя свой профиль.]]></ACCOUNT_LOGIN><VIEW><![CDATA[Смотреть]]></VIEW><CATEGORY><![CDATA[Категория:]]></CATEGORY><EMAIL><![CDATA[Эл. почта]]></EMAIL><BTNNEXT><![CDATA[Далее]]></BTNNEXT><BTNPREVLABEL><![CDATA[Назад]]></BTNPREVLABEL><BTNSAVE><![CDATA[?????????]]></BTNSAVE><BTNSAVEE><![CDATA[Сохранить]]></BTNSAVEE><REMOVESAVEDITEMS><![CDATA[Удалить отмеченные]]></REMOVESAVEDITEMS><SHOWSAVEDITEMS><![CDATA[Показать отмеченные]]></SHOWSAVEDITEMS><ADV_SEARCH_BODY><![CDATA[Поиск по типу кузова]]></ADV_SEARCH_BODY><SELECT_TYPE><![CDATA[Тип камеры]]></SELECT_TYPE><ALLNEWS><![CDATA[Все]]></ALLNEWS><REQ_COMPANY_EMAIL><![CDATA[Введите эл. адрес]]></REQ_COMPANY_EMAIL><ANSWER><![CDATA[Ответить]]></ANSWER><VOTE><![CDATA[Ответить]]></VOTE><SERVICE_ADD_SUCCESS_ADED><![CDATA[Спасибо! Объявление успешно добавлено. После проверки объявления нашим модератором, оно будет опубликовано на страницах Транспорт.]]></SERVICE_ADD_SUCCESS_ADED><SERVICES><![CDATA[Транспорт]]></SERVICES><CHOOSE_PIC><![CDATA[Выбрать картину]]></CHOOSE_PIC><SELECT_ANSWER><![CDATA[Выберите ответ]]></SELECT_ANSWER><LITER><![CDATA[л]]></LITER><INPUT_CODE><![CDATA[Введите код с картинки]]></INPUT_CODE><EDIT_PROFILE><![CDATA[Изменить]]></EDIT_PROFILE><MY_CAR><![CDATA[Моя машина]]></MY_CAR><USER_INFO><![CDATA[Информация]]></USER_INFO><UZER_INFO><![CDATA[Информация]]></UZER_INFO><UZER_INFO><![CDATA[Информация]]></UZER_INFO><SHOWALL><![CDATA[Показать все]]></SHOWALL><KM><![CDATA[км]]></KM><WITH_US><![CDATA[С нами уже]]></WITH_US><DAYS><![CDATA[дней]]></DAYS><USER_PREV><![CDATA[Назад]]></USER_PREV><USER_PREV><![CDATA[Назад]]></USER_PREV><USER_PREV><![CDATA[Назад]]></USER_PREV><OTHER_CITY><![CDATA[или другой город]]></OTHER_CITY><CONTACT_PERSON><![CDATA[Контактное лицо]]></CONTACT_PERSON><COUNTRY><![CDATA[Страна]]></COUNTRY><DEVELOPED><![CDATA[Developed by]]></DEVELOPED><DEVELOPED><![CDATA[Developed by]]></DEVELOPED><FILED_CAR_BRAND_MODEL_REQUIRED><![CDATA[Выберите модель]]></FILED_CAR_BRAND_MODEL_REQUIRED><PHONE1_REQUIRED><![CDATA[Введите тел.номер]]></PHONE1_REQUIRED><USER_PHONE1_CODE><![CDATA[Введите только цифры]]></USER_PHONE1_CODE><TECHNICAL_INSP><![CDATA[Технический осмотр транспортных средств]]></TECHNICAL_INSP><TECH_CENTER><![CDATA[Станция технического осмотра]]></TECH_CENTER><NAVI_USERS><![CDATA[Пользователь]]></NAVI_USERS><PROFILECREATE><![CDATA[Создание профиля компании]]></PROFILECREATE><LOGO><![CDATA[Лого]]></LOGO><CREATE><![CDATA[Создать]]></CREATE><REQ_COMPANY_TITLE><![CDATA[Введите имя]]></REQ_COMPANY_TITLE><REQ_COMPANY_ADRESS><![CDATA[Введите адрес]]></REQ_COMPANY_ADRESS><REQ_COMPANY_PHONE><![CDATA[Введите номер телефона]]></REQ_COMPANY_PHONE><DIG_COMPANY_PHONE><![CDATA[Введите только цифры]]></DIG_COMPANY_PHONE><ABOUTCOMP><![CDATA[О компании]]></ABOUTCOMP><ADS_NUMBER><![CDATA[Номер объявления]]></ADS_NUMBER><VIEWED><![CDATA[Просмотров]]></VIEWED><METALIC><![CDATA[Металик]]></METALIC><TECHNICAL_CALC><![CDATA[Техосмотр]]></TECHNICAL_CALC><ECO_CALCULATOR><![CDATA[Экология (CO)]]></ECO_CALCULATOR><ECO_CALCULATOR><![CDATA[Экология (CO)]]></ECO_CALCULATOR><ECO_CALCULATOR><![CDATA[Экология (CO)]]></ECO_CALCULATOR><ECO_CALCULATOR><![CDATA[Экология (CO)]]></ECO_CALCULATOR><PROP_CALC><![CDATA[Налог на имущество ТС]]></PROP_CALC><PAY><![CDATA[Тип ТС]]></PAY><RESULT><![CDATA[Результат:]]></RESULT><K_CENT><![CDATA[Тип двигателя]]></K_CENT><TRANSPORT_TYPE><![CDATA[Тип ТС]]></TRANSPORT_TYPE><POWER><![CDATA[Мощность двигателя (л. с)]]></POWER><TRANSPORT_YEAR><![CDATA[Год выпуска]]></TRANSPORT_YEAR><INSERT_VALID_POWER><![CDATA[Все поля обязательны к заполнению]]></INSERT_VALID_POWER><INSERT_VALID_POWER><![CDATA[Все поля обязательны к заполнению]]></INSERT_VALID_POWER><CALCULATE><![CDATA[CALCULATE1]]></CALCULATE><CALCULATE><![CDATA[Рассчитать]]></CALCULATE><APPA_CALCULATOR><![CDATA[АППА]]></APPA_CALCULATOR><OBJECTIVE><![CDATA[Цель использования]]></OBJECTIVE><DRIVER_AGE_DRIVING_EXPERIENCE><![CDATA[Возраст и стаж вождения водителя]]></DRIVER_AGE_DRIVING_EXPERIENCE><TM_TYPE_MOTOR_POWER_HORSEPOWER><![CDATA[Мощность двигателя (л.с.)]]></TM_TYPE_MOTOR_POWER_HORSEPOWER><INSUREANCE_DURATION><![CDATA[Длительность страховки]]></INSUREANCE_DURATION><HAS_TRAILER><![CDATA[С прицепом]]></HAS_TRAILER><NO_TRAILER><![CDATA[Нет]]></NO_TRAILER><WITH_TRAILER><![CDATA[Да]]></WITH_TRAILER><CARSALE><![CDATA[Продажа  Автомобилей]]></CARSALE><VALID_COMPANY_EMAIL><![CDATA[Введите правильный адрес эл.почты]]></VALID_COMPANY_EMAIL><USER_LOGIN_ACTION><![CDATA[Логин]]></USER_LOGIN_ACTION><VIEW_COUNT><![CDATA[Смотрели:]]></VIEW_COUNT><VIEW_COUNT><![CDATA[Смотрели:]]></VIEW_COUNT><SOURCE><![CDATA[Истохник:]]></SOURCE><TIMES><![CDATA[раз]]></TIMES><IMAGES><![CDATA[Галерея]]></IMAGES><OFFER_CREDIT><![CDATA[В кредит]]></OFFER_CREDIT><CHANGE_YES><![CDATA[Обменяется]]></CHANGE_YES><CHANGE_NO><![CDATA[Не обменяется]]></CHANGE_NO><CREDIT_YES><![CDATA[Можно в кредит]]></CREDIT_YES><CREDIT_NO><![CDATA[Только наличными]]></CREDIT_NO><NOCUSTOM><![CDATA[Растаможен]]></NOCUSTOM><HASCUSTOM><![CDATA[Не растаможен]]></HASCUSTOM><CONFIRM><![CDATA[Потжердить удаление]]></CONFIRM><ADD_ADVERT><![CDATA[Добавить объявление]]></ADD_ADVERT><ADD_CAR><![CDATA[Продать]]></ADD_CAR><SHOW_ALL><![CDATA[Показать все]]></SHOW_ALL><FINDEDSCARS><![CDATA[Найдено %s машин ]]></FINDEDSCARS><OFFER_CUSTOM><![CDATA[Разтаможивание]]></OFFER_CUSTOM><OFFER_DEADLINE><![CDATA[Срок показа объявления]]></OFFER_DEADLINE><LIMIT_OVERFLOW><![CDATA[Лимит исчерпан]]></LIMIT_OVERFLOW><SUPPORT><![CDATA[Support]]></SUPPORT><AUTHOR><![CDATA[Author]]></AUTHOR><ADVERTISING><![CDATA[Реклама]]></ADVERTISING></ru>
